GonumMatrixIO/GonumIO.py
GonumMatrixIO/__init__.py
gonummatrixio-0.0.9.dist-info/METADATA
gonummatrixio-0.0.9.dist-info/WHEEL
gonummatrixio-0.0.9.dist-info/licenses/LICENSE
gonummatrixio-0.0.9.dist-info/RECORD
