Metadata-Version: 2.1
Name: GonumMatrixIO
Version: 0.0.9
Summary: A package to define functions that allow for easy read/writing of binary files used by golang's Gonum
Project-URL: Homepage, https://github.com/hmcalister/gonum-matrix-io
Project-URL: Bug Tracker, https://github.com/hmcalister/gonum-matrix-io/issues
Author-email: Hayden McAlister <haydenmcalister49@gmail.com>
License-File: LICENSE
Classifier: License :: OSI Approved :: MIT License
Classifier: Operating System :: OS Independent
Classifier: Programming Language :: Python :: 3
Requires-Python: >=3.7
